ascii_live_menu/__init__.py
ascii_live_menu/main.py
ascii_live_menu-0.26.525.dist-info/LICENSE
ascii_live_menu-0.26.525.dist-info/METADATA
ascii_live_menu-0.26.525.dist-info/WHEEL
ascii_live_menu-0.26.525.dist-info/entry_points.txt
ascii_live_menu-0.26.525.dist-info/top_level.txt
ascii_live_menu-0.26.525.dist-info/RECORD
