Metadata-Version: 2.1
Name: ascii_live_menu
Version: 0.26.525
Summary: Description
Home-page: https://github.com/KelvenVS/ASCII_Live_Menu.git
Author: Kelven Vilela
Author-email: kelvenserejo@gmail.com
Requires-Python: >=3.1
License-File: LICENSE
